zope.configuration-5.0.1-py3.11-nspkg.pth
zope/configuration/__init__.py
zope/configuration/_compat.py
zope/configuration/config.py
zope/configuration/docutils.py
zope/configuration/exceptions.py
zope/configuration/fields.py
zope/configuration/interfaces.py
zope/configuration/name.py
zope/configuration/xmlconfig.py
zope/configuration/zopeconfigure.py
zope/configuration/tests/__init__.py
zope/configuration/tests/bad.py
zope/configuration/tests/conditions.py
zope/configuration/tests/conditions.zcml
zope/configuration/tests/directives.py
zope/configuration/tests/nested.py
zope/configuration/tests/notyet.py
zope/configuration/tests/sample.zcml
zope/configuration/tests/schema.zcml
zope/configuration/tests/simple.py
zope/configuration/tests/simple.zcml
zope/configuration/tests/test___init__.py
zope/configuration/tests/test_config.py
zope/configuration/tests/test_docs.py
zope/configuration/tests/test_docutils.py
zope/configuration/tests/test_fields.py
zope/configuration/tests/test_name.py
zope/configuration/tests/test_xmlconfig.py
zope/configuration/tests/test_zopeconfigure.py
zope/configuration/tests/victim.py
zope/configuration/tests/excludedemo/__init__.py
zope/configuration/tests/excludedemo/configure.zcml
zope/configuration/tests/excludedemo/spam.zcml
zope/configuration/tests/excludedemo/sub/__init__.py
zope/configuration/tests/excludedemo/sub/configure.zcml
zope/configuration/tests/samplepackage/NamedForClass.py
zope/configuration/tests/samplepackage/__init__.py
zope/configuration/tests/samplepackage/bar.zcml
zope/configuration/tests/samplepackage/bar1.zcml
zope/configuration/tests/samplepackage/bar2.zcml
zope/configuration/tests/samplepackage/bar21.zcml
zope/configuration/tests/samplepackage/baro.zcml
zope/configuration/tests/samplepackage/baro2.zcml
zope/configuration/tests/samplepackage/baz1.zcml
zope/configuration/tests/samplepackage/baz2.zcml
zope/configuration/tests/samplepackage/baz3.zcml
zope/configuration/tests/samplepackage/configure.zcml
zope.configuration-5.0.1.dist-info/LICENSE.txt
zope.configuration-5.0.1.dist-info/METADATA
zope.configuration-5.0.1.dist-info/WHEEL
zope.configuration-5.0.1.dist-info/namespace_packages.txt
zope.configuration-5.0.1.dist-info/top_level.txt
zope.configuration-5.0.1.dist-info/RECORD
